{"users":[{"nickname":"mix晴子","message":"哈哈哈哈哈哈哈哈哈","data":"2019-08-01 12:25:17"},{"message":"我爱你思密达","data":"2019-08-01 12:25:17","nickname":"mix晴子"},{"message":"我爱你三千次","data":"2019-08-01 14:56:16","nickname":"mix晴子"},{"message":"今天又是充满希望的一天","data":"2019-08-01 14:59:46","nickname":"采蘑菇的小姑娘"},{"message":"我是要成为海贼王的男人啊","data":"2019-08-01 21:19:14","nickname":"mix晴子"},{"message":"j今天也是狗狗顺顺的一天哦","data":"2019-08-02 12:19:54","nickname":"mix狗顺"},{"message":"狗顺you mother boom","data":"2019-08-02 12:20:30","nickname":"mix晴子"},{"message":"狗蛋儒\r\n","data":"2019-08-02 12:59:34","nickname":"Dogru"}]}